odoo/addons/website_sale_require_legal/README.rst
odoo/addons/website_sale_require_legal/__init__.py
odoo/addons/website_sale_require_legal/__manifest__.py
odoo/addons/website_sale_require_legal/controllers/__init__.py
odoo/addons/website_sale_require_legal/controllers/main.py
odoo/addons/website_sale_require_legal/i18n/de.po
odoo/addons/website_sale_require_legal/i18n/es.po
odoo/addons/website_sale_require_legal/i18n/fi.po
odoo/addons/website_sale_require_legal/i18n/hr.po
odoo/addons/website_sale_require_legal/i18n/it.po
odoo/addons/website_sale_require_legal/i18n/sl.po
odoo/addons/website_sale_require_legal/i18n/website_sale_require_legal.pot
odoo/addons/website_sale_require_legal/readme/CONFIGURE.md
odoo/addons/website_sale_require_legal/readme/CONTEXT.md
odoo/addons/website_sale_require_legal/readme/CONTRIBUTORS.md
odoo/addons/website_sale_require_legal/readme/DESCRIPTION.md
odoo/addons/website_sale_require_legal/readme/ROADMAP.md
odoo/addons/website_sale_require_legal/readme/USAGE.md
odoo/addons/website_sale_require_legal/static/description/address-enable.png
odoo/addons/website_sale_require_legal/static/description/icon.png
odoo/addons/website_sale_require_legal/static/description/index.html
odoo/addons/website_sale_require_legal/static/description/payment-enable.png
odoo/addons/website_sale_require_legal/static/src/scss/website_sale_require_legal.scss
odoo/addons/website_sale_require_legal/static/tests/tours/tour.esm.js
odoo/addons/website_sale_require_legal/templates/website_sale.xml
odoo/addons/website_sale_require_legal/tests/__init__.py
odoo/addons/website_sale_require_legal/tests/test_ui.py
odoo_addon_website_sale_require_legal-18.0.1.0.0.2.dist-info/METADATA
odoo_addon_website_sale_require_legal-18.0.1.0.0.2.dist-info/WHEEL
odoo_addon_website_sale_require_legal-18.0.1.0.0.2.dist-info/top_level.txt
odoo_addon_website_sale_require_legal-18.0.1.0.0.2.dist-info/RECORD
